ds_caselaw_utils/.gitignore
ds_caselaw_utils/__init__.py
ds_caselaw_utils/courts.py
ds_caselaw_utils/data/README.md
ds_caselaw_utils/data/court_names.yaml
ds_caselaw_utils/data/markdown/description/eat.md
ds_caselaw_utils/data/markdown/description/ewca.md
ds_caselaw_utils/data/markdown/description/ewca_civ.md
ds_caselaw_utils/data/markdown/description/ewca_crim.md
ds_caselaw_utils/data/markdown/description/ewcc.md
ds_caselaw_utils/data/markdown/description/ewcop.md
ds_caselaw_utils/data/markdown/description/ewcr.md
ds_caselaw_utils/data/markdown/description/ewfc.md
ds_caselaw_utils/data/markdown/description/ewhc.md
ds_caselaw_utils/data/markdown/description/ewhc_admin.md
ds_caselaw_utils/data/markdown/description/ewhc_admlty.md
ds_caselaw_utils/data/markdown/description/ewhc_ch.md
ds_caselaw_utils/data/markdown/description/ewhc_comm.md
ds_caselaw_utils/data/markdown/description/ewhc_fam.md
ds_caselaw_utils/data/markdown/description/ewhc_ipec.md
ds_caselaw_utils/data/markdown/description/ewhc_kb.md
ds_caselaw_utils/data/markdown/description/ewhc_mercantile.md
ds_caselaw_utils/data/markdown/description/ewhc_pat.md
ds_caselaw_utils/data/markdown/description/ewhc_scco.md
ds_caselaw_utils/data/markdown/description/ewhc_tcc.md
ds_caselaw_utils/data/markdown/description/ftt_claims.md
ds_caselaw_utils/data/markdown/description/ftt_pc.md
ds_caselaw_utils/data/markdown/description/ftt_phl.md
ds_caselaw_utils/data/markdown/description/ftt_transport.md
ds_caselaw_utils/data/markdown/description/paac.md
ds_caselaw_utils/data/markdown/description/poac.md
ds_caselaw_utils/data/markdown/description/siac.md
ds_caselaw_utils/data/markdown/description/ukftt.md
ds_caselaw_utils/data/markdown/description/ukftt_credit.md
ds_caselaw_utils/data/markdown/description/ukftt_estate.md
ds_caselaw_utils/data/markdown/description/ukftt_grc.md
ds_caselaw_utils/data/markdown/description/ukftt_hesc.md
ds_caselaw_utils/data/markdown/description/ukftt_tc.md
ds_caselaw_utils-4.0.0.dist-info/LICENSE.md
ds_caselaw_utils-4.0.0.dist-info/METADATA
ds_caselaw_utils-4.0.0.dist-info/WHEEL
ds_caselaw_utils-4.0.0.dist-info/RECORD
