Metadata-Version: 2.1
Name: ds-caselaw-utils
Version: 4.0.0
Summary: Utilities for the National Archives Caselaw project
Home-page: https://github.com/nationalarchives/ds-caselaw-utils
License: MIT
Keywords: national archives,caselaw
Author: Nick Jackson
Author-email: nick@dxw.com
Requires-Python: >=3.12,<4.0
Classifier: License :: OSI Approved :: MIT License
Classifier: Programming Language :: Python :: 3
Requires-Dist: markdown-it-py (>=4.0.0,<5.0.0)
Requires-Dist: mdit-py-plugins (>=0.5.0,<0.6.0)
Requires-Dist: ruamel.yaml (>=0.19.0,<0.20.0)
Requires-Dist: typing-extensions (>=4.12.2,<5.0.0)
